AUTHORS.rst
CONTRIBUTING.rst
HISTORY.rst
LICENSE
MANIFEST.in
README.rst
setup.cfg
setup.py
docs/Makefile
docs/authors.rst
docs/conf.py
docs/contributing.rst
docs/history.rst
docs/index.rst
docs/installation.rst
docs/make.bat
docs/readme.rst
docs/usage.rst
moma_django/__init__.py
moma_django/exceptions.py
moma_django/fields.py
moma_django/manager.py
moma_django/models.py
moma_django/query.py
moma_django/query_utils.py
moma_django/queryset.py
moma_django.egg-info/PKG-INFO
moma_django.egg-info/SOURCES.txt
moma_django.egg-info/dependency_links.txt
moma_django.egg-info/not-zip-safe
moma_django.egg-info/requires.txt
moma_django.egg-info/top_level.txt
moma_django/management/commands/__init__.py
moma_django/management/commands/loaddata_mongo.py
moma_example/__init__.py
moma_example/manage.py
moma_example/bootstrapform/__init__.py
moma_example/bootstrapform/meta.py
moma_example/bootstrapform/models.py
moma_example/bootstrapform/templates/bootstrapform/field.html
moma_example/bootstrapform/templates/bootstrapform/form.html
moma_example/bootstrapform/templatetags/__init__.py
moma_example/bootstrapform/templatetags/bootstrap.py
moma_example/data/__init__.py
moma_example/data/admin.py
moma_example/data/forms.py
moma_example/data/models.py
moma_example/data/tests.py
moma_example/data/views.py
moma_example/media/bootstrap/css/bootstrap-theme.css
moma_example/media/bootstrap/css/bootstrap-theme.min.css
moma_example/media/bootstrap/css/bootstrap.css
moma_example/media/bootstrap/css/bootstrap.min.css
moma_example/media/bootstrap/fonts/glyphicons-halflings-regular.eot
moma_example/media/bootstrap/fonts/glyphicons-halflings-regular.svg
moma_example/media/bootstrap/fonts/glyphicons-halflings-regular.ttf
moma_example/media/bootstrap/fonts/glyphicons-halflings-regular.woff
moma_example/media/bootstrap/js/bootstrap.js
moma_example/media/bootstrap/js/bootstrap.min.js
moma_example/moma_example/__init__.py
moma_example/moma_example/settings.py
moma_example/moma_example/settings_local.py
moma_example/moma_example/urls.py
moma_example/moma_example/views.py
moma_example/moma_example/wsgi.py
moma_example/templates/_navbar.html
moma_example/templates/about.html
moma_example/templates/base.html
