Metadata-Version: 1.0
Name: moma-django
Version: 0.1.1
Summary: MoMa-Django provides native Django ORM and admin support for Mongo DB.
Home-page: https://github.com/gadio/moma-django
Author: Gadi Oren
Author-email: gadi.oren.1@gmail.com
License: GPL
Keywords: moma-django,mongodb,django
Platform: UNKNOWN
Classifier: Development Status :: 4 - Beta
Classifier: Environment :: Web Environment
Classifier: Framework :: Django
Classifier: Intended Audience :: Developers
Classifier: License :: OSI Approved :: BSD License
Classifier: Operating System :: OS Independent
Classifier: Programming Language :: Python :: 2.6
Classifier: Programming Language :: Python :: 2.7
Classifier: Topic :: Internet :: WWW/HTTP
Classifier: Topic :: Internet :: WWW/HTTP :: Dynamic Content
Classifier: Topic :: Software Development :: Libraries :: Python Modules
